django_allauth_goodreads-0.0.1.dist-info/METADATA
django_allauth_goodreads-0.0.1.dist-info/RECORD
django_allauth_goodreads-0.0.1.dist-info/WHEEL
django_allauth_goodreads-0.0.1.dist-info/top_level.txt
goodreads_auth/__init__.py
goodreads_auth/api.py
goodreads_auth/models.py
goodreads_auth/provider.py
goodreads_auth/tests.py
goodreads_auth/urls.py
goodreads_auth/views.py
